ssh_switch/__init__.py
ssh_switch/main.py
ssh_switch-0.2.0.dist-info/LICENSE
ssh_switch-0.2.0.dist-info/METADATA
ssh_switch-0.2.0.dist-info/WHEEL
ssh_switch-0.2.0.dist-info/entry_points.txt
ssh_switch-0.2.0.dist-info/top_level.txt
ssh_switch-0.2.0.dist-info/RECORD
